textcleaner_partha/__init__.py
textcleaner_partha/add_abbreviation.py
textcleaner_partha/preprocess.py
textcleaner_partha/abbreviation_mappings/common.json
textcleaner_partha/abbreviation_mappings/legal.json
textcleaner_partha/abbreviation_mappings/medical.json
textcleaner_partha/abbreviation_mappings/slang.json
textcleaner_partha/abbreviation_mappings/telecom.json
textcleaner_partha-1.1.2.dist-info/licenses/LICENSE
textcleaner_partha-1.1.2.dist-info/METADATA
textcleaner_partha-1.1.2.dist-info/WHEEL
textcleaner_partha-1.1.2.dist-info/top_level.txt
textcleaner_partha-1.1.2.dist-info/RECORD
