Metadata-Version: 2.4
Name: textcleaner-partha
Version: 1.1.2
Summary: A lightweight and reusable text preprocessing package for NLP tasks
Home-page: https://github.com/partha6369/textcleaner
Author: Dr. Partha Majumdar
Author-email: "Dr. Partha Majumdar" <partha.majumdar@icloud.com>
License-Expression: MIT
Keywords: NLP,text preprocessing,lemmatization,contractions,emoji removal,spacy,autocorrect,tokens
Classifier: Development Status :: 3 - Alpha
Classifier: Intended Audience :: Developers
Classifier: Intended Audience :: Education
Classifier: Intended Audience :: Science/Research
Classifier: Topic :: Text Processing
Classifier: Topic :: Software Development :: Libraries :: Python Modules
Classifier: Programming Language :: Python :: 3
Classifier: Operating System :: OS Independent
Requires-Python: >=3.7
License-File: LICENSE
Requires-Dist: spacy>=3.0.0
Requires-Dist: autocorrect>=2.6.1
Requires-Dist: contractions>=0.0.55
Requires-Dist: beautifulsoup4>=4.12.0
Requires-Dist: python-docx>=0.8.11
Requires-Dist: pypdf>=3.0.0
Dynamic: author
Dynamic: home-page
Dynamic: license-file
Dynamic: requires-python
